pySim/__init__.py
pySim/card_handler.py
pySim/card_key_provider.py
pySim/cards.py
pySim/cat.py
pySim/commands.py
pySim/construct.py
pySim/exceptions.py
pySim/filesystem.py
pySim/jsonpath.py
pySim/tlv.py
pySim/ts_102_221.py
pySim/ts_31_102.py
pySim/ts_31_103.py
pySim/ts_51_011.py
pySim/utils.py
pySim/transport/__init__.py
pySim/transport/calypso.py
pySim/transport/modem_atcmd.py
pySim/transport/pcsc.py
pySim/transport/serial.py
pysimcard-1.0.4.data/scripts/pySim-prog.py
pysimcard-1.0.4.data/scripts/pySim-read.py
pysimcard-1.0.4.data/scripts/pySim-shell.py
pysimcard-1.0.4.dist-info/COPYING
pysimcard-1.0.4.dist-info/METADATA
pysimcard-1.0.4.dist-info/WHEEL
pysimcard-1.0.4.dist-info/top_level.txt
pysimcard-1.0.4.dist-info/RECORD
