Metadata-Version: 2.1
Name: pysimcard
Version: 1.0.4
Summary: Tools related to SIM/USIM/ISIM cards
Home-page: https://osmocom.org/projects/pysim/wiki
Author-email: simtrace@lists.osmocom.org
License: GPLv2
Platform: UNKNOWN
Requires-Dist: pyscard
Requires-Dist: serial
Requires-Dist: pytlv
Requires-Dist: cmd2 (<2.0.0,>=1.3.0)
Requires-Dist: jsonpath-ng
Requires-Dist: construct (>=2.9)
Requires-Dist: bidict
Requires-Dist: gsm0338
